tensorsim/__init__.py
tensorsim/sim.py
tensorsim-0.0.1.dist-info/LICENSE
tensorsim-0.0.1.dist-info/METADATA
tensorsim-0.0.1.dist-info/WHEEL
tensorsim-0.0.1.dist-info/top_level.txt
tensorsim-0.0.1.dist-info/RECORD
