Metadata-Version: 2.1
Name: tensorsim
Version: 0.0.1
Summary: Simulate predictions by a simulated accuracy
Home-page: https://github.com/MedleyLabs/tensorsim
Author: Eric Yates
Author-email: eric@medleyagency.com
License: MIT License        
Platform: UNKNOWN
License-File: LICENSE
